LICENSE
README.rst
setup.py
crypto_crypto_two1.egg-info/PKG-INFO
crypto_crypto_two1.egg-info/SOURCES.txt
crypto_crypto_two1.egg-info/dependency_links.txt
crypto_crypto_two1.egg-info/entry_points.txt
crypto_crypto_two1.egg-info/requires.txt
crypto_crypto_two1.egg-info/top_level.txt
crypto_two1/__init__.py
crypto_two1/cli.py
crypto_two1/util.py
crypto_two1/bitcoin/__init__.py
crypto_two1/bitcoin/block.py
crypto_two1/bitcoin/coinbase.py
crypto_two1/bitcoin/crypto.py
crypto_two1/bitcoin/exceptions.py
crypto_two1/bitcoin/hash.py
crypto_two1/bitcoin/script.py
crypto_two1/bitcoin/script_interpreter.py
crypto_two1/bitcoin/txn.py
crypto_two1/bitcoin/utils.py
crypto_two1/bitrequests/__init__.py
crypto_two1/bitrequests/bitrequests.py
crypto_two1/bitserv/__init__.py
crypto_two1/bitserv/models.py
crypto_two1/bitserv/payment_methods.py
crypto_two1/bitserv/payment_server.py
crypto_two1/bitserv/django/__init__.py
crypto_two1/bitserv/django/decorator.py
crypto_two1/bitserv/django/models.py
crypto_two1/bitserv/django/urls.py
crypto_two1/bitserv/django/views.py
crypto_two1/bitserv/flask/__init__.py
crypto_two1/bitserv/flask/decorator.py
crypto_two1/blockchain/__init__.py
crypto_two1/blockchain/base_provider.py
crypto_two1/blockchain/exceptions.py
crypto_two1/blockchain/insight_provider.py
crypto_two1/blockchain/mock_provider.py
crypto_two1/blockchain/twentyone_provider.py
crypto_two1/channels/__init__.py
crypto_two1/channels/blockchain.py
crypto_two1/channels/cli.py
crypto_two1/channels/database.py
crypto_two1/channels/paymentchannel.py
crypto_two1/channels/paymentchannelclient.py
crypto_two1/channels/server.py
crypto_two1/channels/statemachine.py
crypto_two1/channels/walletwrapper.py
crypto_two1/commands/__init__.py
crypto_two1/commands/buy.py
crypto_two1/commands/channels.py
crypto_two1/commands/config.py
crypto_two1/commands/doctor.py
crypto_two1/commands/earn.py
crypto_two1/commands/faucet.py
crypto_two1/commands/flush.py
crypto_two1/commands/help.py
crypto_two1/commands/inbox.py
crypto_two1/commands/join.py
crypto_two1/commands/log.py
crypto_two1/commands/login.py
crypto_two1/commands/market.py
crypto_two1/commands/mine.py
crypto_two1/commands/profile.py
crypto_two1/commands/publish.py
crypto_two1/commands/rate.py
